fustor_agent_sdk/__init__.py
fustor_agent_sdk/interfaces.py
fustor_agent_sdk/models.py
fustor_agent_sdk/utils.py
fustor_agent_sdk-0.2.16.dist-info/METADATA
fustor_agent_sdk-0.2.16.dist-info/WHEEL
fustor_agent_sdk-0.2.16.dist-info/top_level.txt
fustor_agent_sdk-0.2.16.dist-info/RECORD
