Metadata-Version: 2.4
Name: fustor-agent-sdk
Version: 0.2.16
Summary: SDK for Fustor Agent service
License-Expression: MIT
Requires-Dist: fustor-core
Requires-Dist: fustor-registry-client
